MRItaxonomy/NCBI_fetch.py
MRItaxonomy/__init__.py
MRItaxonomy/accession2taxid.py
MRItaxonomy/nnID.py
MRItaxonomy/nucDL.py
MRItaxonomy/protacc2taxid.py
MRItaxonomy/slidingwindow.py
MRItaxonomy/taxid.py
MRItaxonomy/taxid2name.py
MRItaxonomy-1.1.1.dist-info/LICENSE.txt
MRItaxonomy-1.1.1.dist-info/METADATA
MRItaxonomy-1.1.1.dist-info/WHEEL
MRItaxonomy-1.1.1.dist-info/top_level.txt
MRItaxonomy-1.1.1.dist-info/RECORD
