Metadata-Version: 2.1
Name: MRItaxonomy
Version: 1.1.1
Summary: MRIGlobal's taxonomy related operators
Home-page: https://github.com/mriglobal/MRItaxonomy
Author: MRIGlobal Bioinformatics Team
Author-email: biofx@mriglobal.org
License: MIT
Keywords: mriglobal taxonomy ncbi
Classifier: Topic :: Scientific/Engineering :: Bio-Informatics
Classifier: Development Status :: 3 - Alpha
Classifier: Intended Audience :: Developers
Classifier: License :: OSI Approved :: GNU General Public License v3 (GPLv3)
Classifier: Programming Language :: Python
License-File: LICENSE.txt
Requires-Dist: pandas (>=0.19.0)
Requires-Dist: biopython (>=1.7)
Requires-Dist: wget (>=3.2)
Requires-Dist: marisa-trie (>=1.1.0)
